performance_timer/__init__.py
performance_timer/exceptions.py
performance_timer/timer.py
performance_timer-0.1.1.dist-info/WHEEL
performance_timer-0.1.1.dist-info/METADATA
performance_timer-0.1.1.dist-info/RECORD
